teserak/__init__.py
teserak/py.typed
teserak/w3c/__init__.py
teserak/w3c/models/__init__.py
teserak/w3c/models/xmlmime.py
teserak/w3c/models/xop.py
teserak/w3c/soap/__init__.py
teserak/w3c/soap/context.py
teserak/w3c/soap/handler.py
teserak/w3c/soap/multipart.py
teserak/w3c/soap/types.py
teserak/w3c/soap/utils.py
teserak/w3c/soap/version11/__init__.py
teserak/w3c/soap/version12/__init__.py
teserak_soap_server-0.0.9.dist-info/LICENSE.md
teserak_soap_server-0.0.9.dist-info/METADATA
teserak_soap_server-0.0.9.dist-info/WHEEL
teserak_soap_server-0.0.9.dist-info/top_level.txt
teserak_soap_server-0.0.9.dist-info/RECORD
