Metadata-Version: 2.1
Name: teserak-soap-server
Version: 0.0.9
Summary: The ASGI SOAP Server.
Home-page: https://github.com/teserak/teserak-soap-server
Author: Konrad Rymczak
Author-email: me@teserak.com
License: BSD
Platform: UNKNOWN
Classifier: License :: OSI Approved :: BSD License
Classifier: Operating System :: OS Independent
Classifier: Topic :: Internet :: WWW/HTTP
Classifier: Programming Language :: Python :: 3.8
Classifier: Programming Language :: Python :: 3.9
Classifier: Programming Language :: Python :: 3.10
Requires-Python: >=3.8
License-File: LICENSE.md
Requires-Dist: starlette (==0.16.0)
Requires-Dist: xsdata (==22.1)
Requires-Dist: python-multipart (==0.0.5)
